mypackage/__init__.py
mypackage/mymodule.py
tests/__init__.py
tests/test_mymodule.py
hsol_package-0.1.0.dist-info/LICENSE
hsol_package-0.1.0.dist-info/METADATA
hsol_package-0.1.0.dist-info/WHEEL
hsol_package-0.1.0.dist-info/top_level.txt
hsol_package-0.1.0.dist-info/RECORD
