Metadata-Version: 2.1
Name: hsol-package
Version: 0.1.0
Summary: A simple example package
Home-page: https://github.com/yourusername/mypackage
Author: Your Name
Author-email: your.email@example.com
License: UNKNOWN
Platform: UNKNOWN
Classifier: Programming Language :: Python :: 3
Classifier: License :: OSI Approved :: MIT License
Classifier: Operating System :: OS Independent
Requires-Python: >=3.6
License-File: LICENSE
